clickhouse_driver/__init__.py
clickhouse_driver/block.py
clickhouse_driver/blockstreamprofileinfo.py
clickhouse_driver/bufferedreader.cpython-313-aarch64-linux-gnu.so
clickhouse_driver/bufferedwriter.cpython-313-aarch64-linux-gnu.so
clickhouse_driver/client.py
clickhouse_driver/clientinfo.py
clickhouse_driver/connection.py
clickhouse_driver/context.py
clickhouse_driver/defines.py
clickhouse_driver/errors.py
clickhouse_driver/log.py
clickhouse_driver/opentelemetry.py
clickhouse_driver/progress.py
clickhouse_driver/protocol.py
clickhouse_driver/queryprocessingstage.py
clickhouse_driver/reader.py
clickhouse_driver/readhelpers.py
clickhouse_driver/result.py
clickhouse_driver/varint.cpython-313-aarch64-linux-gnu.so
clickhouse_driver/writer.py
clickhouse_driver/columns/__init__.py
clickhouse_driver/columns/arraycolumn.py
clickhouse_driver/columns/base.py
clickhouse_driver/columns/boolcolumn.py
clickhouse_driver/columns/datecolumn.py
clickhouse_driver/columns/datetimecolumn.py
clickhouse_driver/columns/decimalcolumn.py
clickhouse_driver/columns/enumcolumn.py
clickhouse_driver/columns/exceptions.py
clickhouse_driver/columns/floatcolumn.py
clickhouse_driver/columns/intcolumn.py
clickhouse_driver/columns/intervalcolumn.py
clickhouse_driver/columns/ipcolumn.py
clickhouse_driver/columns/jsoncolumn.py
clickhouse_driver/columns/largeint.cpython-313-aarch64-linux-gnu.so
clickhouse_driver/columns/lowcardinalitycolumn.py
clickhouse_driver/columns/mapcolumn.py
clickhouse_driver/columns/nestedcolumn.py
clickhouse_driver/columns/nothingcolumn.py
clickhouse_driver/columns/nullablecolumn.py
clickhouse_driver/columns/nullcolumn.py
clickhouse_driver/columns/service.py
clickhouse_driver/columns/simpleaggregatefunctioncolumn.py
clickhouse_driver/columns/stringcolumn.py
clickhouse_driver/columns/tuplecolumn.py
clickhouse_driver/columns/util.py
clickhouse_driver/columns/uuidcolumn.py
clickhouse_driver/columns/numpy/__init__.py
clickhouse_driver-0.2.10.dist-info/METADATA
clickhouse_driver-0.2.10.dist-info/WHEEL
clickhouse_driver-0.2.10.dist-info/top_level.txt
clickhouse_driver-0.2.10.dist-info/RECORD
clickhouse_driver-0.2.10.dist-info/licenses/LICENSE
