Metadata-Version: 2.4
Name: clickhouse-driver
Version: 0.2.10
Summary: Python driver with native interface for ClickHouse
Home-page: https://github.com/mymarilyn/clickhouse-driver
Author: Konstantin Lebedev
Author-email: kostyan.lebedev@gmail.com
License: MIT
Project-URL: Documentation, https://clickhouse-driver.readthedocs.io
Project-URL: Changes, https://github.com/mymarilyn/clickhouse-driver/blob/master/CHANGELOG.md
Keywords: ClickHouse db database cloud analytics
Classifier: Development Status :: 4 - Beta
Classifier: Environment :: Console
Classifier: Intended Audience :: Developers
Classifier: Intended Audience :: Information Technology
Classifier: License :: OSI Approved :: MIT License
Classifier: Operating System :: OS Independent
Classifier: Programming Language :: SQL
Classifier: Programming Language :: Python :: 3
Classifier: Programming Language :: Python :: 3.9
Classifier: Programming Language :: Python :: 3.10
Classifier: Programming Language :: Python :: 3.11
Classifier: Programming Language :: Python :: 3.12
Classifier: Programming Language :: Python :: 3.13
Classifier: Programming Language :: Python :: 3.14
Classifier: Programming Language :: Python :: Implementation :: PyPy
Classifier: Topic :: Database
Classifier: Topic :: Software Development
Classifier: Topic :: Software Development :: Libraries
Classifier: Topic :: Software Development :: Libraries :: Application Frameworks
Classifier: Topic :: Software Development :: Libraries :: Python Modules
Classifier: Topic :: Scientific/Engineering :: Information Analysis
Requires-Python: >=3.9, <4
License-File: LICENSE
Requires-Dist: pytz
Requires-Dist: tzlocal
Provides-Extra: lz4
Requires-Dist: lz4<=3.0.1; implementation_name == "pypy" and extra == "lz4"
Requires-Dist: lz4; implementation_name != "pypy" and extra == "lz4"
Requires-Dist: clickhouse-cityhash>=1.0.2.1; extra == "lz4"
Provides-Extra: zstd
Requires-Dist: zstd; extra == "zstd"
Requires-Dist: clickhouse-cityhash>=1.0.2.1; extra == "zstd"
Provides-Extra: numpy
Requires-Dist: numpy>=1.12.0; extra == "numpy"
Requires-Dist: pandas>=0.24.0; extra == "numpy"
Dynamic: author
Dynamic: author-email
Dynamic: classifier
Dynamic: description
Dynamic: home-page
Dynamic: keywords
Dynamic: license
Dynamic: license-file
Dynamic: project-url
Dynamic: provides-extra
Dynamic: requires-dist
Dynamic: requires-python
Dynamic: summary
